<YealinkIPPhoneDirectory>
  <DirectoryEntry>
    <Name>Fax Zentral 1</Name>
    <Telephone>030494004778</Telephone>
  </DirectoryEntry>
  <DirectoryEntry>
    <Name>WBL Fr. Elli Bryka</Name>
    <Telephone>030494004783</Telephone>
  </DirectoryEntry>
  <DirectoryEntry>
    <Name>stellv. PDL Fr. Heil</Name>
    <Telephone>030494004765</Telephone>
  </DirectoryEntry>
  <DirectoryEntry>
    <Name>Sanimedius Apotheke</Name>
    <Telephone>0306881707010</Telephone>
  </DirectoryEntry>
  <DirectoryEntry>
    <Name>Fax Sanimedius Apotheke</Name>
    <Telephone>0306881707090</Telephone>
  </DirectoryEntry>
</YealinkIPPhoneDirectory>
